Metadata-Version: 1.0
Name: hhrtest
Version: 0.0.3
Summary: hhrtest
Home-page: https://github.com/hhr66
Author: hhrtest
Author-email: hhr66@qq.com
License: MIT Licence
Keywords: pip,hhrtest,hhr,test
Platform: any
